mongodbrdg
