Metadata-Version: 2.1
Name: mongodbrdg
Version: 0.2a3
Summary: MongoDB RDG - Random data generator for MongoDB
Home-page: https://github.com/jdrumgoole/mongdb_random_data_generator
Author: Joe Drumgoole
Author-email: joe@joedrumgoole.com
License: Apache 2.0
Keywords: Random Data MongoDB
Platform: UNKNOWN
Classifier: Development Status :: 3 - Alpha
Classifier: Intended Audience :: Developers
Classifier: License :: OSI Approved :: Apache Software License
Classifier: Programming Language :: Python :: 3.7
Requires-Python: >3.7
